empiarreader/__init__.py
empiarreader/cli.py
empiarreader/empiar/__init__.py
empiarreader/empiar/empiar.py
empiarreader/intake_source/__init__.py
empiarreader/intake_source/mrcsource.py
empiarreader/intake_source/starsource.py
empiarreader/utilities/__init__.py
empiarreader/utilities/download.py
empiarreader/utilities/search.py
empiarreader-0.0.17.dist-info/licenses/LICENSE
empiarreader-0.0.17.dist-info/METADATA
empiarreader-0.0.17.dist-info/WHEEL
empiarreader-0.0.17.dist-info/entry_points.txt
empiarreader-0.0.17.dist-info/top_level.txt
empiarreader-0.0.17.dist-info/RECORD
