Metadata-Version: 2.4
Name: empiarreader
Version: 0.0.17
Summary: EMPIARReader provides utilities to lazily load data from EMPIAR into a machine-learning-friendly dataset format or to locally download the files.
Author-email: mooniean <bcostagomes@turing.ac.uk>, ots22 <ostrickson@turing.ac.uk>
Project-URL: Homepage, https://github.com/ccpem/empiarreader
Project-URL: Bug Tracker, https://github.com/ccpem/empiarreader
Requires-Python: >=3.8
License-File: LICENSE
Requires-Dist: intake>=0.6.6
Requires-Dist: bs4>=0.0.1
Requires-Dist: matplotlib>=3.6.1
Requires-Dist: requests>=2.28.1
Requires-Dist: scikit-image>=0.19.3
Requires-Dist: xarray>=2022.9.0
Requires-Dist: mrcfile>=1.4.3
Requires-Dist: starfile>=0.4.11
Requires-Dist: intake-xarray>=0.6.1
Requires-Dist: aiohttp>=3.8.3
Requires-Dist: setuptools>=67.7.2
Requires-Dist: pre-commit>=3.3.3
Requires-Dist: numpy<2,>=1.23.3
Requires-Dist: jinja2>=3.1.0
Provides-Extra: doc
Requires-Dist: Sphinx>=5.0.0; extra == "doc"
Requires-Dist: pydata-sphinx-theme>=0.7; extra == "doc"
Provides-Extra: dev
Requires-Dist: pytest>=6.2.5; extra == "dev"
Dynamic: license-file
